odineye/__init__.py
odineye/maps_downloaders/__init__.py
odineye/maps_downloaders/google_maps_downloader.py
odineye/maps_downloaders/maps_downloader.py
odineye/url_downloader/__init__.py
odineye/url_downloader/url_downloader.py
odineye/url_downloader/url_downloader_thread.py
odineye/utils/__init__.py
odineye/utils/coordinates_convertion.py
odineye/utils/image_utils.py
odineye-0.1.5.dist-info/LICENSE
odineye-0.1.5.dist-info/METADATA
odineye-0.1.5.dist-info/WHEEL
odineye-0.1.5.dist-info/RECORD
