Metadata-Version: 2.1
Name: odineye
Version: 0.1.5
Summary: A package for downloading satellite maps. Odin sees everything.
License: GNU General Public License v3.0
Author: NaturalStupidlty
Requires-Python: >=3.8
Classifier: License :: Other/Proprietary License
Classifier: Programming Language :: Python :: 3
Classifier: Programming Language :: Python :: 3.8
Classifier: Programming Language :: Python :: 3.9
Classifier: Programming Language :: Python :: 3.10
Classifier: Programming Language :: Python :: 3.11
Classifier: Programming Language :: Python :: 3.12
Requires-Dist: numpy (>=1.24.4)
Requires-Dist: pillow (>=10.2.0)
Requires-Dist: tqdm (>=4.66.2)
